{
  "name": "lighthouse-gnosis.avado.dnp.dappnode.eth",
  "version": "0.0.2",
  "upstream": "v5.0.0",
  "title": "Lighthouse-Gnosis",
  "description": "An open-source Ethereum consensus client, written in Rust and maintained by Sigma Prime.",
  "avatar": "/ipfs/QmXimBvXWsL8xzuNoift9ygFdCHAMoj2e8vDeeMbgpX8gC",
  "type": "service",
  "autoupdate": true,
  "image": {
    "volumes": [
      "data:/data"
    ],
    "ports": [
      "9011:9011/udp",
      "9011:9011"
    ],
    "environment": [
      "EXTRA_OPTS_BEACON_NODE=",
      "EXTRA_OPTS_VALIDATOR_CLIENT="
    ],
    "restart": "always"
  },
  "author": "heeckhau",
  "license": "Apache(c)",
  "dependencies": {},
  "ui": {
    "OnboardingWizard": {
      "url": "http://lighthouse-gnosis.my.ava.do",
      "external": true
    }
  },
  "links": {
    "OnboardingWizard": "http://lighthouse-gnosis.my.ava.do",
    "HomePage": "https://lighthouse-book.sigmaprime.io/"
  }
}